setup.cfg
setup.py
kokoropy/__init__.py
kokoropy/asset.py
kokoropy/controller.py
kokoropy/kokoro.py
kokoropy/model.py
kokoropy/scaffold.py
kokoropy.egg-info/PKG-INFO
kokoropy.egg-info/SOURCES.txt
kokoropy.egg-info/dependency_links.txt
kokoropy.egg-info/requires.txt
kokoropy.egg-info/top_level.txt