Metadata-Version: 1.1
Name: kokoropy
Version: 0.0.1
Summary: MVC web framework based on Bottle
Home-page: https://github.com/goFrendiAsgard/kokoropy
Author: Go Frendi Gunawan
Author-email: gofrendiasgard@gmail.com
License: LICENSE.txt
Download-URL: https://github.com/goFrendiAsgard/kokoropy/tarball/0.1
Keywords: web,mvc
Platform: UNKNOWN
